Requesters/InfinityRequester.py
Requesters/InfinityScroller.py
Requesters/Requester.py
Requesters/RequesterException.py
Requesters/Response.py
Requesters/__init__.py
Requesters/test.py
WebBrowser/SeleniumBrowser.py
WebBrowser/__init__.py
WebBrowser/SiteRegistration/CookieRegistration.py
WebBrowser/SiteRegistration/IRegistration.py
WebBrowser/SiteRegistration/__init__.py
WebBrowser/WebAction/ActionScroll.py
WebBrowser/WebAction/IAction.py
WebBrowser/WebAction/__init__.py
WebBrowser/drivers/chromedriver_win
WebBrowser/drivers/manual.md
amis_web_requester-0.4.dist-info/LICENCE
amis_web_requester-0.4.dist-info/METADATA
amis_web_requester-0.4.dist-info/WHEEL
amis_web_requester-0.4.dist-info/top_level.txt
amis_web_requester-0.4.dist-info/RECORD
